README.rst
setup.py
wrimg/__init__.py
wrimg/cli.py
wrimg/devices.py
wrimg/size.py
wrimg.egg-info/PKG-INFO
wrimg.egg-info/SOURCES.txt
wrimg.egg-info/dependency_links.txt
wrimg.egg-info/entry_points.txt
wrimg.egg-info/requires.txt
wrimg.egg-info/top_level.txt