Metadata-Version: 1.1
Name: wrimg
Version: 0.1
Summary: An alternative to dd for writing images to sd-cards
Home-page: http://github.com/mbr/wrimg
Author: Marc Brinkmann
Author-email: git@marcbrinkmann.de
License: MIT
Platform: UNKNOWN
Classifier: Programming Language :: Python :: 2
